marshmallow_custom_jsonapi/__init__.py
marshmallow_custom_jsonapi/exceptions.py
marshmallow_custom_jsonapi/fields.py
marshmallow_custom_jsonapi/flask.py
marshmallow_custom_jsonapi/schema.py
marshmallow_custom_jsonapi/utils.py
marshmallow_custom_jsonapi-0.0.2.dist-info/LICENSE
marshmallow_custom_jsonapi-0.0.2.dist-info/METADATA
marshmallow_custom_jsonapi-0.0.2.dist-info/WHEEL
marshmallow_custom_jsonapi-0.0.2.dist-info/top_level.txt
marshmallow_custom_jsonapi-0.0.2.dist-info/RECORD
